pandas_ml/__init__.py
pandas_ml/compat.py
pandas_ml/tools.py
pandas_ml/version.py
pandas_ml/confusion_matrix/__init__.py
pandas_ml/confusion_matrix/abstract.py
pandas_ml/confusion_matrix/bcm.py
pandas_ml/confusion_matrix/cm.py
pandas_ml/confusion_matrix/stats.py
pandas_ml/confusion_matrix/test/__init__.py
pandas_ml/confusion_matrix/test/test_confusion_matrix.py
pandas_ml/core/__init__.py
pandas_ml/core/accessor.py
pandas_ml/core/base.py
pandas_ml/core/frame.py
pandas_ml/core/generic.py
pandas_ml/core/groupby.py
pandas_ml/core/series.py
pandas_ml/imbaccessors/__init__.py
pandas_ml/imbaccessors/base.py
pandas_ml/imbaccessors/test/__init__.py
pandas_ml/imbaccessors/test/test_imbalance.py
pandas_ml/misc/__init__.py
pandas_ml/misc/patsy_wraps.py
pandas_ml/misc/test/__init__.py
pandas_ml/misc/test/test_patsy.py
pandas_ml/skaccessors/__init__.py
pandas_ml/skaccessors/base.py
pandas_ml/skaccessors/cluster.py
pandas_ml/skaccessors/covariance.py
pandas_ml/skaccessors/cross_decomposition.py
pandas_ml/skaccessors/decomposition.py
pandas_ml/skaccessors/ensemble.py
pandas_ml/skaccessors/feature_extraction.py
pandas_ml/skaccessors/feature_selection.py
pandas_ml/skaccessors/gaussian_process.py
pandas_ml/skaccessors/isotonic.py
pandas_ml/skaccessors/linear_model.py
pandas_ml/skaccessors/manifold.py
pandas_ml/skaccessors/metrics.py
pandas_ml/skaccessors/model_selection.py
pandas_ml/skaccessors/neighbors.py
pandas_ml/skaccessors/pipeline.py
pandas_ml/skaccessors/preprocessing.py
pandas_ml/skaccessors/svm.py
pandas_ml/skaccessors/test/__init__.py
pandas_ml/skaccessors/test/test_base.py
pandas_ml/skaccessors/test/test_calibration.py
pandas_ml/skaccessors/test/test_cluster.py
pandas_ml/skaccessors/test/test_covariance.py
pandas_ml/skaccessors/test/test_cross_decomposition.py
pandas_ml/skaccessors/test/test_datasets.py
pandas_ml/skaccessors/test/test_decomposition.py
pandas_ml/skaccessors/test/test_discriminant_analysis.py
pandas_ml-0.6.1.dist-info/DESCRIPTION.rst
pandas_ml-0.6.1.dist-info/METADATA
pandas_ml-0.6.1.dist-info/RECORD
pandas_ml-0.6.1.dist-info/WHEEL
pandas_ml-0.6.1.dist-info/metadata.json
pandas_ml-0.6.1.dist-info/top_level.txt
