Metadata-Version: 1.0
Name: pandas_ml
Version: 0.6.1
Summary: pandas, scikit-learn and xgboost integration
Home-page: http://pandas-ml.readthedocs.org/en/stable
Author: sinhrks
Author-email: sinhrks@gmail.com
License: BSD
Platform: UNKNOWN
